<dsx>

    <scene root="root" axis_length="0"/>

    <views default="vista1">

        <perspective id="vista1" near="0.1" far="500" angle="0.4">
            <from x="30" y="30" z="30"/>
            <to x="0" y="0" z="0"/>
        </perspective>
        <perspective id="vista2" near="0.1" far="300" angle="0.2">
            <from x="40" y="40" z="40"/>
            <to x="0" y="0" z="0"/>
        </perspective>
        <perspective id="vista3" near="0.1" far="200" angle="0.4">
            <from x="40" y="10" z="5"/>
            <to x="0" y="0" z="5"/>
        </perspective>
        <perspective id="vista4" near="0.1" far="200" angle="0.4">
            <from x="5" y="10" z="40"/>
            <to x="5" y="0" z="0"/>
        </perspective>
        <perspective id="vista5" near="0.1" far="200" angle="0.4">
            <from x="5" y="40" z="5"/>
            <to x="5" y="0" z="5"/>
        </perspective>
        <perspective id="vista6" near="0.1" far="200" angle="0.4">
            <from x="20" y="10" z="10"/>
            <to x="0" y="0" z="5"/>
        </perspective>
        <perspective id="vista7" near="0.1" far="200" angle="0.4">
            <from x="3" y="10" z="20"/>
            <to x="3" y="0" z="0"/>
        </perspective>

    </views>

    <illumination doublesided="1" local="0">

        <ambient r="0.1" g="0.1" b="0.1" a="1"/>
        <background r="0" g="0" b="0" a="1"/>

    </illumination>

    <lights>

        <!-- 1 - True   0 - False -->
        <omni id="Light 0" enabled="1">
            <location x="2" y="3" z="3" w="1"/>
            <ambient r="0" g="0" b="0" a="0"/>
            <diffuse r="1" g="1" b="1" a="1"/>
            <specular r="0" g="0" b="0" a="0"/>
        </omni>

        <omni id="Light 1" enabled="1">
            <location x="0" y="3" z="0" w="1.0"/>
            <ambient r="0" g="0" b="0" a="1"/>
            <diffuse r="1" g="1" b="1" a="1"/>
            <specular r="0" g="0" b="0" a="0"/>
        </omni>

        <omni id="Light 2" enabled="1">
            <location x="10.5" y="10" z="10" w="1.0"/>
            <ambient r="0" g="0" b="0" a="1"/>
            <diffuse r="1" g="1" b="1" a="1"/>
            <specular r="1" g="1" b="1" a="1"/>
        </omni>

        <omni id="Light 3" enabled="1">
            <location x="4" y="10" z="10" w="1.0"/>
            <ambient r="0" g="0" b="0" a="0"/>
            <diffuse r="1" g="1" b="1" a="1"/>
            <specular r="1" g="1" b="1" a="1"/>
        </omni>

        <spot id="Light 4" enabled="0" angle="20" exponent="2">
            <target x="0" y="0" z="0"/>
            <location x="1" y="13.5" z="15"/>
            <ambient r="0.8" g="0.9" b="1" a="1"/>
            <diffuse r="1" g="0" b="0" a="1"/>
            <specular r="1" g="0" b="0" a="1"/>
        </spot>

    </lights>

    <textures>
        <texture id="bag1" file="img/bag1.jpg" length_s="1" length_t="1"/>
        <texture id="metal" file="img/metal.jpeg" length_s="1" length_t="1"/>
        <texture id="carpet" file="img/carpet.jpg" length_s="1" length_t="1"/>
        <texture id="bag2" file="img/bag2.jpg" length_s="1" length_t="1"/>
        <texture id="bag3" file="img/bag3.jpg" length_s="1" length_t="1"/>
        <texture id="bag4" file="img/bag4.jpg" length_s="1" length_t="1"/>
        <texture id="bagdoor" file="img/bagdoor.jpg" length_s="1" length_t="1"/>
        <texture id="bag5" file="img/bag5.jpeg" length_s="1" length_t="1"/>
        <texture id="bag7" file="img/bag7.jpg" length_s="1" length_t="1"/>
        <texture id="terminal" file="img/terminal.png" length_s="1" length_t="1"/>
        <texture id="tvArrivals" file="img/tvArrivals.png" length_s="1" length_t="1"/>
        <texture id="danger" file="img/danger.jpg" length_s="1" length_t="1"/>
        <texture id="foodmachine" file="img/food.jpg" length_s="1" length_t="1"/>
        <texture id="signalbagage" file="img/signal.png" length_s="1" length_t="1"/>
        <texture id="ball" file="img/ball.jpg" length_s="1" length_t="1"/>
        <texture id="donut" file="img/donut.jpg" length_s="1" length_t="1"/>
        <texture id="floor" file="img/floor.jpeg" length_s="1" length_t="1"/>
        <texture id="signal" file="img/signal.jpg" length_s="1" length_t="1"/>
        <texture id="cone" file="img/conePattern.png" length_s="1" length_t="1"/>
        <texture id="caution" file="img/caution.png" length_s="1" length_t="1"/>
        <texture id="Ofloor" file="img/outfloor.jpg" length_s="1" length_t="1"/>



    </textures>

    <materials>
        <material id="1">
            <emission r="0" g="0" b="0" a="1"/>
            <ambient r="0.2" g="0.2" b="0.2" a="1"/>
            <diffuse r="1" g="1" b="1" a="1"/>
            <specular r="0.5" g="0.5" b="0.5" a="1"/>
            <shininess value="20"/>
        </material>

        <material id="2">
            <emission r="0" g="0" b="0" a="0"/>
            <ambient r="0" g="0" b="0" a="0"/>
            <diffuse r="1" g="1" b="1" a="1"/>
            <specular r="0.1" g="0.1" b="0.1" a="1"/>
            <shininess value="1"/>
        </material>

        <material id="wallMaterial">
            <emission r="0.7" g="0.7" b="0.7" a="1"/>
            <ambient r="0.6" g="0.6" b="0.5" a="1"/>
            <diffuse r="0.6" g="0.6" b="0.5" a="1"/>
            <specular r="0.6" g="0.6" b="0.5" a="1"/>
            <shininess value="20"/>
        </material>

        <material id="wallMaterial2">
            <emission r="0.7" g="0.7" b="0.7" a="1"/>
            <ambient r="0.7" g="0.7" b="0.8" a="1"/>
            <diffuse r="0.7" g="0.7" b="0.8" a="1"/>
            <specular r="0.7" g="0.7" b="0.8" a="1"/>
            <shininess value="20"/>
        </material>

        <material id="floorMaterial">
            <emission r="0.5" g="0.5" b="0.5" a="1"/>
            <ambient r="0.9" g="0.9" b="0.8" a="1"/>
            <diffuse r="0.9" g="0.9" b="0.8" a="1"/>
            <specular r="0.9" g="0.9" b="0.8" a="1"/>
            <shininess value="20"/>
        </material>

        <material id="floorMaterial2">
            <emission r="0.5" g="0.5" b="0.5" a="1"/>
            <ambient r="0.4" g="0.4" b="0.4" a="1"/>
            <diffuse r="0.4" g="0.4" b="0.4" a="1"/>
            <specular r="0.4" g="0.4" b="0.4" a="1"/>
            <shininess value="20"/>
        </material>

        <material id="yellowMaterial">
            <emission r="0.9" g="1" b="0.1" a="1"/>
            <ambient r="0.9" g="1" b="0.1" a="1"/>
            <diffuse r="0.9" g="1" b="0.1" a="1"/>
            <specular r="0.9" g="1" b="0.1" a="1"/>
            <shininess value="20"/>
        </material>

        <material id="orange">
            <emission r="0.5" g="0.5" b="0.5" a="1"/>
            <ambient r="0.8" g="0.4" b="0" a="1"/>
            <diffuse r="0.8" g="0.4" b="0" a="1"/>
            <specular r="0.8" g="0.4" b="0" a="1"/>
            <shininess value="20"/>
        </material>

        <material id="white">
            <emission r="0.5" g="0.5" b="0.5" a="1"/>
            <ambient r="1" g="1" b="1" a="1"/>
            <diffuse r="1" g="1" b="1" a="1"/>
            <specular r="1" g="1" b="1" a="1"/>
            <shininess value="1"/>
        </material>

    </materials>

    <transformations>
        <transformation id="1">
            <translate x="4" y="4" z="4"/>
            <rotate axis="x" angle="30"/>
            <scale x="1" y="1" z="1"/>
        </transformation>

        <transformation id="2">
            <translate x="0" y="0" z="0"/>
            <rotate axis="x" angle="0"/>
            <scale x="0" y="0" z="0"/>
        </transformation>

        <transformation id="donut">
            <translate x="0.4" y="0.52" z="3.7"/>
            <scale x="0.02" y="0.02" z="0.02"/>
            <rotate axis="x" angle="90"/>
        </transformation>

    </transformations>

    <!-- novo bloco de animacao -->
    <animations>
        <!-- podem existir zero ou mais nós "animation" -->
        <!-- span é o tempo, em segundos, que a animação deve -->
        <!-- demorar. Nesta versão do formato DSX, type pode ter -->
        <!-- o valor "linear" ou "circular"; na animacao circular -->
        <!-- os angulos sao expressos em graus  -->

        <animation id="3" span="1" type="linear">
            <controlpoint xx="2" yy="3" zz="3" />
            <controlpoint xx="2" yy="2" zz="2" />
            <controlpoint xx="1" yy="1" zz="2" />
            <controlpoint xx="1" yy="0" zz="1" />
        </animation>

        <animation id="2" span="1" type="linear">
            <controlpoint xx="1" yy="0" zz="1" />
            <controlpoint xx="1" yy="1" zz="2" />
            <controlpoint xx="2" yy="2" zz="2" />
            <controlpoint xx="2" yy="3" zz="3" />
        </animation>
        <animation id="1" span="10" type="circular" center="0 0 0" radius="10" startang="20" rotang="0" />
    </animations>


    <primitives>
        <primitive id="cylindricBag">
            <cylinder base="1" top="1" height="4" slices="26" stacks="4"/>
        </primitive>

        <primitive id="tableTop">
            <cylinder base="2" top="2" height="0.05" slices="26" stacks="4"/>
        </primitive>

        <primitive id="donut">
            <torus inner="1" outer="3" slices="20" loops="20"/>
        </primitive>

        <primitive id="1">
            <rectangle x1="0.5" y1="0.5" x2="-0.5" y2="-0.5"/>
        </primitive>

        <primitive id="roolerBag">
            <cylinder base="0.1" top="0.1" height="0.1" slices="26" stacks="4"/>
        </primitive>

        <primitive id="SphereBall">
            <sphere radius="0.15" slices="100" stacks="100"/>
        </primitive>

        <primitive id="triangle">
            <triangle x1="-0.5" y1="0" z1="0" x2="0" y2="1" z2="0" x3="0.5" y3="0" z3="0"/>
        </primitive>

        <primitive id="cone">
          <cylinder base="0" top="0.2" height="0.8" slices="26" stacks="4"/>
        </primitive>

        <primitive id="vehicle">
           <vehicle/>
        </primitive>

    </primitives>

    <components>

        <component id="root">
            <transformation></transformation>
            <materials>
                <material id="2"/>
            </materials>
            <texture id="none"/>
            <children>
                <componentref id="BoardFlights"/>
                <componentref id="CarpetAllBags"/>
                <componentref id="OtherBags1"/>
                <componentref id="OtherBags2"/>
                <componentref id="OtherBags3"/>
                <componentref id="OtherBags4"/>
                <componentref id="OtherBags5"/>
                <componentref id="OtherBags6"/>
                <componentref id="walls"/>
                <componentref id="floor"/>
                <componentref id="CompleteFirstchair"/>
                <componentref id="CompleteFirstchair2"/>
                <componentref id="table"/>
                <componentref id="dangerWarning"/>
                <componentref id="foodMachine"/>
                <componentref id="signalBagageClaim"/>
                <componentref id="donutOnTable"/>
                <componentref id="signalWarning"/>
                <componentref id="Trafficcone"/>
                <componentref id="wetFloorSign"/>
                <componentref id="vehicle"/>
            </children>
        </component>

        <component id="vehicle">
            <transformation>
                <translate x="9.5" y="0.2" z="5"/>
            </transformation>

            <materials>
                <material id="white"/>
            </materials>

            <texture id="none"/>

            <children>
                <componentref id="car"/>
                <componentref id="CarHelpbottom"/>
                <componentref id="carBags1"/>
                <componentref id="carBags2"/>
            </children>
        </component>

        <component id="car">
            <transformation>
                  <scale x="0.35" y="0.35" z="0.35"/>
            </transformation>
            <materials>
                <material id="inherit"/>
            </materials>
            <texture id="metal"/>
            <children>
                  <primitiveref id="vehicle"/>
            </children>
        </component>

        <component id="carBags1">
            <transformation>
                <translate x="0" y="0.6" z="-2.5"/>
            </transformation>

            <materials>
                <material id="inherit"/>
            </materials>

            <texture id="bag1"/>

            <children>
                <componentref id="RectangleBag"/>
            </children>
        </component>

        <component id="carBags2">
            <transformation>
                <translate x="0" y="0.6" z="-3"/>
                <rotate axis="y" angle="45"/>
            </transformation>

            <materials>
                <material id="inherit"/>
            </materials>

            <texture id="bag3"/>

            <children>
                <componentref id="RectangleBag"/>
            </children>
        </component>

        <component id="CarHelpbottom">
            <transformation>
                <translate x="0" y="0.15" z="-3"/>
                <scale x="1" y="0.15" z="1.9"/>
            </transformation>

            <materials>
                <material id="inherit"/>
            </materials>

            <texture id="metal"/>

            <children>
                <componentref id="cubo"/>
            </children>
        </component>

        <component id="wetFloorSign">
            <transformation>
              <translate x="3" y="0.3" z="6"/>
              <rotate axis="y" angle="45"/>
              <scale x="0.5" y="0.5" z="1"/>
            </transformation>
            <materials>
                <material id="1"/>
            </materials>
            <texture id="caution"/>
            <children>
              <componentref id="wetFloorSign1"/>
              <componentref id="wetFloorSign2"/>
            </children>
        </component>

        <component id="wetFloorSign1">
            <transformation>
                <translate x="0" y="0.5" z="0.2"/>
                <rotate axis="x" angle="-12"/>
                <rotate axis="y" angle="180"/>
                <scale x="1.5" y="2" z="1"/>
            </transformation>
            <materials>
                <material id="1"/>
            </materials>
            <texture id="caution"/>
            <children>
                <primitiveref id="1"/>

            </children>
        </component>

        <component id="wetFloorSign2">
            <transformation>
                <translate x="0" y="0.5" z="-0.2"/>
                <rotate axis="x" angle="12"/>
                <scale x="1.5" y="2" z="1"/>
            </transformation>
            <materials>
                <material id="1"/>
            </materials>
            <texture id="caution"/>
            <children>
                <primitiveref id="1"/>
            </children>
        </component>

        <component id="Trafficcone">
            <transformation>
              <translate x="2.5" y="0.8" z="7"/>
            </transformation>
            <materials>
                <material id="white"/>
            </materials>
            <texture id="cone"/>
            <children>
                <componentref id="coneBase"/>
                <componentref id="cone"/>
            </children>
        </component>

        <component id="coneBase">
            <transformation>
              <translate x="0" y="-0.76" z="0"/>
              <rotate axis="x" angle="90"/>
              <scale x="0.4" y="0.4" z="0.4"/>
            </transformation>
            <materials>
                <material id="orange"/>
            </materials>
            <texture id="none"/>
            <children>
                <primitiveref id="1"/>
            </children>
        </component>

        <component id="cone">
            <transformation>
                <rotate axis="y" angle="90"/>
                <translate x="0" y="-0.2" z="0"/>
                <rotate axis="x" angle="90"/>
                <scale x="0.7" y="0.7" z="0.7"/>
            </transformation>
            <materials>
                <material id="white"/>
            </materials>
            <texture id="cone"/>
            <children>
                <primitiveref id="cone"/>
            </children>
        </component>

        <component id="signalWarning">
            <transformation>
                <translate x="0.1" y="2" z="6"/>
                <rotate axis="y" angle="90"/>
            </transformation>
            <materials>
                <material id="1"/>
            </materials>
            <texture id="signal"/>
            <children>
                <primitiveref id="triangle"/>
            </children>
        </component>

        <component id="donutOnTable">
            <transformation>
              <!--  <translate x="0.4" y="0.52" z="3.7"/>
                <scale x="0.02" y="0.02" z="0.02"/>
                <rotate axis="x" angle="90"/>-->
                <transformationref id="donut"/>
            </transformation>
            <materials>
                <material id="1"/>
            </materials>
            <texture id="donut"/>
            <children>
                <primitiveref id="donut"/>
            </children>
        </component>

        <component id="foodMachine">
            <transformation>
                <translate x="7" y="1.3" z="0.5"/>
                <scale x="0.5" y="0.5" z="0.5"/>
            </transformation>
            <materials>
                <material id="1"/>
            </materials>
            <texture id="none"/>
            <children>
                <componentref id="cuboMachine"/>
            </children>
        </component>

        <component id="cuboMachine">
            <transformation>
                <scale x="1.8" y="5" z="1.5"/>
            </transformation>
            <materials>
                <material id="1"/>
            </materials>
            <texture id="inherit"/>
            <children>
                <componentref id="lado1"/>
                <componentref id="lado2machine"/>
                <componentref id="lado3"/>
                <componentref id="lado4"/>
                <componentref id="lado5"/>
                <componentref id="lado6"/>
            </children>
        </component>

        <component id="lado2machine">
            <transformation>
                <translate x="0" y="0" z="0.5"/>
                <rotate axis="y" angle="180"/>
            </transformation>

            <materials>
                <material id="2"/>
            </materials>

            <texture id="foodmachine"/>

            <children>
                <primitiveref id="1"/>
            </children>
        </component>

        <component id="dangerWarning">
            <transformation></transformation>
            <materials>
                <material id="1"/>
            </materials>
            <texture id="danger"/>
            <children>
                <componentref id="dangerWarningleft"/>
                <componentref id="dangerWarningRight"/>
                <componentref id="dangerWarningFront"/>
            </children>
        </component>

        <component id="dangerWarningleft">
            <transformation>
                <translate x="1.6" y="0.05" z="2.3"/>
                <scale x="0.05" y="1" z="4.5"/>
                <rotate axis="x" angle="90"/>
            </transformation>
            <materials>
                <material id="1"/>
            </materials>
            <texture id="inherit"/>
            <children>
                <primitiveref id="1"/>
            </children>
        </component>

        <component id="dangerWarningRight">
            <transformation>
                <translate x="5.3" y="0.05" z="2.3"/>
                <scale x="0.05" y="1" z="4.5"/>
                <rotate axis="x" angle="90"/>
            </transformation>
            <materials>
                <material id="1"/>
            </materials>
            <texture id="inherit"/>
            <children>
                <primitiveref id="1"/>
            </children>
        </component>

        <component id="dangerWarningFront">
            <transformation>
                <translate x="3.45" y="0.05" z="4.55"/>
                <rotate axis="y" angle="90"/>
                <scale x="0.05" y="1" z="3.75"/>
                <rotate axis="x" angle="90"/>
            </transformation>
            <materials>
                <material id="1"/>
            </materials>
            <texture id="inherit"/>
            <children>
                <primitiveref id="1"/>
            </children>
        </component>

        <component id="OtherBags1">
            <transformation>
                <translate x="1.5" y="0.35" z="5.2"/>
                <rotate axis="y" angle="20"/>
            </transformation>
            <materials>
                <material id="1"/>
            </materials>
            <texture id="bag2"/>
            <children>
                <componentref id="RectangleBag"/>
            </children>
        </component>

        <component id="OtherBags2">
            <transformation>
                <translate x="1" y="0.45" z="5"/>
                <rotate axis="y" angle="45"/>
                <scale x="1.3" y="1.3" z="1.3"/>
            </transformation>
            <materials>
                <material id="1"/>
            </materials>
            <texture id="bag3"/>
            <children>
                <componentref id="RectangleBag"/>
            </children>
        </component>

        <component id="OtherBags5">
            <transformation>
                <translate x="7" y="0.45" z="6"/>
                <rotate axis="y" angle="10"/>
                <scale x="1.3" y="1.3" z="1.3"/>
            </transformation>
            <materials>
                <material id="1"/>
            </materials>
            <texture id="bag5"/>
            <children>
                <componentref id="RectangleBag"/>
            </children>
        </component>

        <component id="OtherBags6">
            <transformation>
                <translate x="7.4" y="0.45" z="5.7"/>
                <rotate axis="y" angle="-20"/>
                <scale x="1" y="1" z="1"/>
            </transformation>
            <materials>
                <material id="1"/>
            </materials>
            <texture id="bag1"/>
            <children>
                <componentref id="RectangleBag"/>
            </children>
        </component>

        <component id="OtherBags3">
            <transformation>
                <translate x="1" y="0.19" z="5.5"/>
                <rotate axis="y" angle="10"/>
                <scale x="1" y="1" z="0.8"/>
            </transformation>
            <materials>
                <material id="1"/>
            </materials>
            <texture id="bag1"/>
            <children>
                <componentref id="cylindricBagWithHandel"/>
            </children>
        </component>

        <component id="OtherBags4">
            <transformation>
                <translate x="0.7" y="0.19" z="5.9"/>
                <rotate axis="y" angle="50"/>
            </transformation>
            <materials>
                <material id="1"/>
            </materials>
            <texture id="ball"/>
            <children>
                <primitiveref id="SphereBall"/>
            </children>
        </component>

        <component id="BoardFlights">
            <transformation>
                <translate x="4" y="3" z="0.2"/>
                <scale x="2" y="1.5" z="2"/>
                <rotate axis="y" angle="180"/>
            </transformation>
            <materials>
                <material id="1"/>
            </materials>
            <texture id="tvArrivals"/>
            <children>
                <primitiveref id="1"/>
            </children>
        </component>

        <component id="signalBagageClaim">
            <transformation>
                <translate x="0.1" y="2.7" z="3.5"/>
                <rotate axis="y" angle="-90"/>
                <scale x="2" y="0.7" z="2"/>
            </transformation>
            <materials>
                <material id="1"/>
            </materials>
            <texture id="signalbagage"/>
            <children>
                <primitiveref id="1"/>
            </children>
        </component>

        <component id="table">
            <transformation>
                <translate x="0.5" y="0.25" z="3.7"/>
                <scale x="0.2" y="0.3" z="0.2"/>
            </transformation>
            <materials>
                <material id="1"/>
            </materials>
            <texture id="metal"/>
            <children>
                <componentref id="tablecomponents"/>
            </children>
        </component>

        <component id="tablecomponents">
            <transformation></transformation>
            <materials>
                <material id="1"/>
            </materials>
            <texture id="inherit"/>
            <children>
                <componentref id="topTable"/>
                <componentref id="baseTable"/>
                <componentref id="secondbaseTable"/>
            </children>
        </component>

        <component id="topTable">
            <transformation>
                <translate x="0" y="0.75" z="0"/>
                <rotate axis="x" angle="-90"/>
            </transformation>
            <materials>
                <material id="1"/>
            </materials>
            <texture id="inherit"/>
            <children>
                <primitiveref id="tableTop"/>
            </children>
        </component>

        <component id="secondbaseTable">
            <transformation>
                <scale x="0.4" y="0.4" z="0.4"/>
                <translate x="0" y="-1.9" z="0"/>
                <rotate axis="x" angle="-90"/>
            </transformation>
            <materials>
                <material id="1"/>
            </materials>
            <texture id="inherit"/>
            <children>
                <primitiveref id="tableTop"/>
            </children>
        </component>

        <component id="baseTable">
            <transformation>
                <scale x="0.2" y="1.5" z="0.2"/>
            </transformation>
            <materials>
                <material id="1"/>
            </materials>
            <texture id="inherit"/>
            <children>
                <componentref id="cubo"/>
            </children>
        </component>

        <component id="CompleteFirstchair">
            <transformation>
                <translate x="0.5" y="0.45" z="3"/>
            </transformation>
            <materials>
                <material id="1"/>
            </materials>
            <texture id="metal"/>
            <children>
                <componentref id="chair"/>
            </children>
        </component>

        <component id="CompleteFirstchair2">
            <transformation>
                <translate x="7.5" y="0.45" z="3.2"/>
                <rotate axis="y" angle="180"/>
            </transformation>
            <materials>
                <material id="1"/>
            </materials>
            <texture id="metal"/>
            <children>
                <componentref id="chair"/>
            </children>
        </component>

        <component id="chair">
            <transformation>
                <scale x="0.5" y="0.5" z="0.5"/>
                <rotate axis="y" angle="90"/>
            </transformation>
            <materials>
                <material id="1"/>
            </materials>
            <texture id="metal"/>
            <children>
                <componentref id="chair1"/>
                <componentref id="chair2"/>
                <componentref id="chair3"/>
                <componentref id="chair4"/>
                <componentref id="chairfoot1"/>
                <componentref id="chairfoot2"/>
                <componentref id="chairfoot3"/>
                <componentref id="chairfoot4"/>
            </children>
        </component>

        <component id="chairfoot1">
            <transformation>
                <translate x="0" y="-0.41" z="0"/>
                <scale x="0.25" y="0.80" z="0.25"/>
            </transformation>
            <materials>
                <material id="1"/>
            </materials>
            <texture id="metal"/>
            <children>
                <componentref id="cubo"/>
            </children>
        </component>

        <component id="chairfoot2">
            <transformation>
                <translate x="1.2" y="-0.41" z="0"/>
                <scale x="0.25" y="0.80" z="0.25"/>
            </transformation>
            <materials>
                <material id="1"/>
            </materials>
            <texture id="metal"/>
            <children>
                <componentref id="cubo"/>
            </children>
        </component>

        <component id="chairfoot3">
            <transformation>
                <translate x="2.4" y="-0.41" z="0"/>
                <scale x="0.25" y="0.80" z="0.25"/>
            </transformation>
            <materials>
                <material id="1"/>
            </materials>
            <texture id="metal"/>
            <children>
                <componentref id="cubo"/>
            </children>
        </component>

        <component id="chairfoot4">
            <transformation>
                <translate x="3.6" y="-0.41" z="0"/>
                <scale x="0.25" y="0.80" z="0.25"/>
            </transformation>
            <materials>
                <material id="1"/>
            </materials>
            <texture id="metal"/>
            <children>
                <componentref id="cubo"/>
            </children>
        </component>

        <component id="chair4">
            <transformation>
                <translate x="3.6" y="0" z="0"/>
            </transformation>
            <materials>
                <material id="1"/>
            </materials>
            <texture id="metal"/>
            <children>
                <componentref id="chairpart1"/>
                <componentref id="chairpart2"/>
            </children>
        </component>

        <component id="chair3">
            <transformation>
                <translate x="2.4" y="0" z="0"/>
            </transformation>
            <materials>
                <material id="1"/>
            </materials>
            <texture id="metal"/>
            <children>
                <componentref id="chairpart1"/>
                <componentref id="chairpart2"/>
            </children>
        </component>

        <component id="chair2">
            <transformation>
                <translate x="1.2" y="0" z="0"/>
            </transformation>
            <materials>
                <material id="1"/>
            </materials>
            <texture id="metal"/>
            <children>
                <componentref id="chairpart1"/>
                <componentref id="chairpart2"/>
            </children>
        </component>

        <component id="chair1">
            <transformation></transformation>
            <materials>
                <material id="1"/>
            </materials>
            <texture id="metal"/>
            <children>
                <componentref id="chairpart1"/>
                <componentref id="chairpart2"/>
            </children>
        </component>

        <component id="chairpart1">
            <transformation>
                <rotate axis="x" angle="-90"/>
                <scale x="1" y="1" z="0.2"/>

            </transformation>
            <materials>
                <material id="1"/>
            </materials>
            <texture id="metal"/>
            <children>
                <componentref id="cubo"/>
            </children>
        </component>

        <component id="chairpart2">
            <transformation>
                <translate x="0" y="0.6" z="-0.4"/>
                <scale x="1" y="1" z="0.2"/>
            </transformation>
            <materials>
                <material id="1"/>
            </materials>
            <texture id="metal"/>
            <children>
                <componentref id="cubo"/>
            </children>
        </component>

        <component id="CarpetAllBags">
            <transformation>
                <translate x="3.5" y="0.17" z="2.2"/>
            </transformation>
            <materials>
                <material id="floorMaterial"/>
            </materials>
            <texture id="metal"/>
            <children>
                <componentref id="Bag1onCarpet"/>
                <componentref id="Bag2onCarpet"/>
                <componentref id="Bag3onCarpet"/>
                <componentref id="BagCarpet"/>
            </children>
        </component>

        <component id="floor">
            <transformation>
                <scale x="11" y="5" z="11"/>
                <rotate axis="x" angle="90"/>
                <translate x="0.5" y="0.5" z="0"/>
            </transformation>
            <materials>
                <material id="floorMaterial"/>
                <material id="floorMaterial2"/>
            </materials>
            <texture id="none"/>
            <children>
                <primitiveref id="1"/>
            </children>
        </component>

        <component id="walls">
            <transformation></transformation>
            <materials>
                <material id="wallMaterial"/>
                <material id="wallMaterial2"/>
            </materials>
            <texture id="none"/>
            <children>
                <componentref id="wall1"/>
                <componentref id="wall2"/>
            </children>
        </component>

        <component id="wall1">
            <transformation>
                <scale x="11" y="5" z="11"/>
                <translate x="0.5" y="0.5" z="0"/>
                <rotate axis="y" angle="180"/>
            </transformation>
            <materials>
                <material id="inherit"/>
            </materials>
            <texture id="none"/>
            <children>
                <primitiveref id="1"/>
            </children>
        </component>

        <component id="wall2">
            <transformation>
                <scale x="11" y="5" z="11"/>
                <rotate axis="y" angle="-90"/>
                <translate x="0.5" y="0.5" z="0"/>
            </transformation>
            <materials>
                <material id="inherit"/>
            </materials>
            <texture id="none"/>
            <children>
                <primitiveref id="1"/>
            </children>
        </component>

        <component id="Bag1onCarpet">
            <transformation>
                <translate x="1.2" y="0.5" z="1.5"/>
            </transformation>
            <materials>
                <material id="1"/>
            </materials>
            <texture id="bag4"/>
            <children>
                <componentref id="RectangleBag"/>
            </children>
        </component>

        <component id="Bag3onCarpet">
            <transformation>
                <translate x="1.2" y="0.3" z="0"/>
                <rotate axis="x" angle="-90"/>
                <rotate axis="z" angle="45"/>
            </transformation>
            <materials>
                <material id="1"/>
            </materials>
            <texture id="bag1"/>
            <children>
                <componentref id="RectangleBag"/>
            </children>
        </component>

        <component id="Bag2onCarpet">
            <transformation>
                <translate x="-0.6" y="0.35" z="1.7"/>
            </transformation>
            <materials>
                <material id="1"/>
            </materials>
            <texture id="bag7"/>
            <children>
                <componentref id="cylindricBagWithHandel"/>
            </children>
        </component>

        <component id="BagCarpet">
            <transformation>
                <scale x="0.6" y="0.6" z="0.6"/>
                <rotate axis="y" angle="-90"/>
            </transformation>
            <materials>
                <material id="1"/>
            </materials>
            <texture id="carpet"/>
            <children>
                <componentref id="carpetStructure1"/>
                <componentref id="carpetStructure2"/>
                <componentref id="carpetStructure3"/>
                <componentref id="bagdoor1"/>
                <componentref id="bagdoor2"/>
                <componentref id="terminalCube"/>
            </children>
        </component>

        <component id="terminalCube">
            <transformation>
                <translate x="0" y="1.1" z="0"/>
                <rotate axis="y" angle="180"/>
            </transformation>
            <materials>
                <material id="1"/>
            </materials>
            <texture id="terminal"/>
            <children>
                <componentref id="cubo"/>
            </children>
        </component>

        <component id="bagdoor1">
            <transformation>
                <translate x="-3.25" y="1" z="1.3"/>
                <rotate axis="y" angle="-90"/>
                <scale x="1.6" y="1.6" z="1.6"/>
            </transformation>
            <materials>
                <material id="1"/>
            </materials>
            <texture id="bagdoor"/>
            <children>
                <primitiveref id="1"/>
            </children>
        </component>

        <component id="bagdoor2">
            <transformation>
                <translate x="-3.25" y="1" z="-1.3"/>
                <rotate axis="y" angle="-90"/>
                <scale x="1.6" y="1.6" z="1.6"/>
            </transformation>
            <materials>
                <material id="1"/>
            </materials>
            <texture id="bagdoor"/>
            <children>
                <primitiveref id="1"/>
            </children>
        </component>

        <component id="carpetStructure1">
            <transformation>
                <scale x="7" y="0.5" z="5"/>
            </transformation>
            <materials>
                <material id="1"/>
            </materials>
            <texture id="carpet"/>
            <children>
                <componentref id="cubo2"/>
            </children>
        </component>

        <component id="carpetStructure2">
            <transformation>
                <translate x="0" y="0.5" z="0"/>
                <scale x="3.5" y="0.3" z="2"/>
            </transformation>
            <materials>
                <material id="1"/>
            </materials>
            <texture id="metal"/>
            <children>
                <componentref id="cubo"/>
            </children>
        </component>

        <component id="carpetStructure3">
            <transformation>
                <translate x="-3.4" y="1.25" z="0"/>
                <scale x="0.2" y="2" z="5"/>
            </transformation>
            <materials>
                <material id="1"/>
            </materials>
            <texture id="metal"/>
            <children>
                <componentref id="cubo"/>
            </children>
        </component>

        <component id="cylindricBagWithHandel">
            <transformation>
                <scale x="0.75" y="0.75" z="0.75"/>
            </transformation>
            <materials>
                <material id="1"/>
            </materials>
            <texture id="inherit"/>
            <children>
                <componentref id="cylindricBag"/>
                <componentref id="cylindricHandel"/>

            </children>
        </component>

        <component id="cylindricBag">
            <transformation>
                <rotate axis="y" angle="-90"/>
                <scale x="0.25" y="0.25" z="0.25"/>
                <translate x="0" y="0" z="-2"/>

            </transformation>
            <materials>
                <material id="1"/>
            </materials>
            <texture id="inherit"/>
            <children>
                <primitiveref id="cylindricBag"/>
            </children>
        </component>

        <component id="cylindricHandel">
            <transformation>
                <translate x="0" y="0.1" z="0"/>
            </transformation>

            <materials>
                <material id="inherit"/>
            </materials>

            <texture id="carpet"/>

            <children>
                <componentref id="cylindricHandel1"/>
                <componentref id="cylindricHandel2"/>
                <componentref id="handel3"/>
            </children>
        </component>

        <component id="cylindricHandel1">
            <transformation>
                <translate x="-0.2" y="0.25" z="0"/>
                <scale x="0.02" y="0.5" z="0.1"/>
            </transformation>

            <materials>
                <material id="inherit"/>
            </materials>

            <texture id="inherit"/>

            <children>
                <componentref id="cubo"/>
            </children>
        </component>

        <component id="cylindricHandel2">
            <transformation>
                <translate x="0.2" y="0.25" z="0"/>
                <scale x="0.02" y="0.5" z="0.1"/>
            </transformation>

            <materials>
                <material id="inherit"/>
            </materials>

            <texture id="inherit"/>

            <children>
                <componentref id="cubo"/>
            </children>
        </component>

        <component id="RectangleBag">
            <transformation>
                <scale x="0.45" y="0.45" z="0.45"/>
            </transformation>
            <materials>
                <material id="2"/>
            </materials>
            <texture id="inherit"/>
            <children>
                <componentref id="bag"/>
                <componentref id="handel"/>
                <componentref id="roolers"/>
            </children>
        </component>

        <component id="roolers">
            <transformation></transformation>
            <materials>
                <material id="2"/>
            </materials>
            <texture id="metal"/>
            <children>
                <componentref id="rooler1"/>
                <componentref id="rooler2"/>
            </children>
        </component>

        <component id="rooler1">
            <transformation>
                <translate x="0.35" y="-0.65" z="0"/>
            </transformation>
            <materials>
                <material id="2"/>
            </materials>
            <texture id="inherit"/>
            <children>
                <primitiveref id="roolerBag"/>
            </children>
        </component>

        <component id="rooler2">
            <transformation>
                <translate x="-0.35" y="-0.65" z="0"/>
            </transformation>
            <materials>
                <material id="2"/>
            </materials>
            <texture id="inherit"/>
            <children>
                <primitiveref id="roolerBag"/>
            </children>
        </component>

        <component id="handel">
            <transformation>
                <translate x="0" y="1" z="-0.1"/>
            </transformation>

            <materials>
                <material id="2"/>
            </materials>

            <texture id="metal"/>

            <children>
                <componentref id="handel1"/>
                <componentref id="handel2"/>
                <componentref id="handel3"/>
            </children>
        </component>

        <component id="handel1">
            <transformation>
                <translate x="-0.2" y="0" z="0"/>
                <scale x="0.02" y="1" z="0.1"/>
            </transformation>

            <materials>
                <material id="2"/>
            </materials>

            <texture id="inherit"/>

            <children>
                <componentref id="cubo"/>
            </children>
        </component>

        <component id="handel2">
            <transformation>
                <translate x="0.2" y="0" z="0"/>
                <scale x="0.02" y="1" z="0.1"/>
            </transformation>

            <materials>
                <material id="2"/>
            </materials>

            <texture id="inherit"/>

            <children>
                <componentref id="cubo"/>
            </children>
        </component>

        <component id="handel3">
            <transformation>
                <translate x="0" y="0.5" z="0"/>
                <scale x="0.5" y="0.02" z="0.1"/>
            </transformation>

            <materials>
                <material id="2"/>
            </materials>

            <texture id="inherit"/>

            <children>
                <componentref id="cubo"/>
            </children>
        </component>

        <component id="bag">
            <transformation>
                <scale x="0.7" y="1.3" z="0.5"/>
            </transformation>

            <materials>
                <material id="2"/>
            </materials>

            <texture id="inherit"/>

            <children>
                <componentref id="cubo"/>
            </children>
        </component>

        <component id="cubo">
            <transformation></transformation>

            <materials>
                <material id="inherit"/>
            </materials>

            <texture id="inherit"/>

            <children>
                <componentref id="lado1"/>
                <componentref id="lado2"/>
                <componentref id="lado3"/>
                <componentref id="lado4"/>
                <componentref id="lado5"/>
                <componentref id="lado6"/>

            </children>
        </component>

        <component id="cubo2">
            <transformation></transformation>

            <materials>
                <material id="inherit"/>
            </materials>

            <texture id="inherit"/>

            <children>
                <componentref id="lado1carpet"/>
                <componentref id="lado2carpet"/>
                <componentref id="lado3carpet"/>
                <componentref id="lado4"/>
                <componentref id="lado5"/>
                <componentref id="lado6"/>

            </children>
        </component>

        <component id="lado1carpet">
            <transformation>
                <translate x="0" y="0" z="-0.5"/>
            </transformation>

            <materials>
                <material id="inherit"/>
            </materials>

            <texture id="metal"/>

            <children>
                <primitiveref id="1"/>
            </children>
        </component>

        <component id="lado1">
            <transformation>
                <translate x="0" y="0" z="-0.5"/>
            </transformation>

            <materials>
                <material id="inherit"/>
            </materials>

            <texture id="inherit"/>

            <children>
                <primitiveref id="1"/>
            </children>
        </component>

        <component id="lado2">
            <transformation>
                <translate x="0" y="0" z="0.5"/>
                <rotate axis="y" angle="180"/>
            </transformation>

            <materials>
                <material id="inherit"/>
            </materials>

            <texture id="inherit"/>

            <children>
                <primitiveref id="1"/>
            </children>
        </component>

        <component id="lado2carpet">
            <transformation>
                <translate x="0" y="0" z="0.5"/>
                <rotate axis="y" angle="180"/>
            </transformation>

            <materials>
                <material id="inherit"/>
            </materials>

            <texture id="metal"/>

            <children>
                <primitiveref id="1"/>
            </children>
        </component>

        <component id="lado3">
            <transformation>
                <translate x="-0.5" y="0" z="0"/>
                <rotate axis="y" angle="90"/>
            </transformation>

            <materials>
                <material id="inherit"/>
            </materials>

            <texture id="inherit"/>

            <children>
                <primitiveref id="1"/>
            </children>
        </component>

        <component id="lado3carpet">
            <transformation>
                <translate x="-0.5" y="0" z="0"/>
                <rotate axis="y" angle="90"/>
            </transformation>

            <materials>
                <material id="inherit"/>
            </materials>

            <texture id="metal"/>

            <children>
                <primitiveref id="1"/>
            </children>
        </component>

        <component id="lado4">
            <transformation>
                <translate x="0" y="-0.5" z="0"/>
                <rotate axis="x" angle="-90"/>
            </transformation>

            <materials>
                <material id="inherit"/>
            </materials>

            <texture id="inherit"/>

            <children>
                <primitiveref id="1"/>
            </children>
        </component>

        <component id="lado5">
            <transformation>
                <translate x="0" y="0.5" z="0"/>
                <rotate axis="x" angle="90"/>
            </transformation>

            <materials>
                <material id="inherit"/>
            </materials>

            <texture id="inherit"/>

            <children>
                <primitiveref id="1"/>
            </children>
        </component>

        <component id="lado6">
            <transformation>
                <translate x="0.5" y="0" z="0"/>
                <rotate axis="y" angle="-90"/>
            </transformation>

            <materials>
                <material id="inherit"/>
            </materials>

            <texture id="inherit"/>

            <children>
                <primitiveref id="1"/>
            </children>
        </component>


    </components>

</dsx>
